{
	"info": {
		"_postman_id": "b6a8c2d1-7e4f-4b5a-9c3d-1e2f3a4b5c6d",
		"name": "Big Shop Backend API (Complete)",
		"description": "Collection complète et corrigée pour tester toutes les APIs de Big Shop Backend",
		"schema": "https://schema.getpostman.com/json/collection/v2.1.0/collection.json"
	},
	"variable": [
		{
			"key": "baseUrl",
			"value": "http://localhost:8081",
			"type": "string"
		},
		{
			"key": "authToken",
			"value": "",
			"type": "string"
		},
		{
			"key": "userId",
			"value": "",
			"type": "string"
		},
		{
			"key": "userEmail",
			"value": "",
			"type": "string"
		},
		{
			"key": "productId",
			"value": "1",
			"type": "string"
		},
		{
			"key": "categoryId",
			"value": "1",
			"type": "string"
		},
		{
			"key": "orderId",
			"value": "",
			"type": "string"
		},
		{
			"key": "addressId",
			"value": "1",
			"type": "string"
		}
	],
	"item": [
		{
			"name": "01. Authentication",
			"item": [
				{
					"name": "Register User",
					"event": [
						{
							"listen": "prerequest",
							"script": {
								"exec": [
									"pm.environment.set(\"randomEmail\", \"user\" + Date.now() + \"@example.com\");"
								],
								"type": "text/javascript"
							}
						},
						{
							"listen": "test",
							"script": {
								"exec": [
									"pm.test(\"Status code is 201\", function () {",
									"    pm.response.to.have.status(201);",
									"});",
									"var jsonData = pm.response.json();",
									"if (jsonData.accessToken) {",
									"    pm.environment.set(\"authToken\", jsonData.accessToken);",
									"    pm.environment.set(\"userId\", jsonData.user.id);",
									"    // Sauvegarde l'email utilisé pour le login futur",
									"    var requestBody = JSON.parse(pm.request.body.raw);",
									"    pm.environment.set(\"userEmail\", requestBody.email);",
									"}"
								],
								"type": "text/javascript"
							}
						}
					],
					"request": {
						"method": "POST",
						"header": [
							{
								"key": "Content-Type",
								"value": "application/json"
							}
						],
						"body": {
							"mode": "raw",
							"raw": "{\n    \"firstName\": \"John\",\n    \"lastName\": \"Doe\",\n    \"email\": \"{{randomEmail}}\",\n    \"password\": \"password123\"\n}"
						},
						"url": {
							"raw": "{{baseUrl}}/auth/register",
							"host": [
								"{{baseUrl}}"
							],
							"path": [
								"auth",
								"register"
							]
						}
					},
					"response": []
				},
				{
					"name": "Login User",
					"event": [
						{
							"listen": "test",
							"script": {
								"exec": [
									"pm.test(\"Status code is 200\", function () {",
									"    pm.response.to.have.status(200);",
									"});",
									"var jsonData = pm.response.json();",
									"if (jsonData.accessToken) {",
									"    pm.environment.set(\"authToken\", jsonData.accessToken);",
									"    pm.environment.set(\"userId\", jsonData.user.id);",
									"}"
								],
								"type": "text/javascript"
							}
						}
					],
					"request": {
						"method": "POST",
						"header": [
							{
								"key": "Content-Type",
								"value": "application/json"
							}
						],
						"body": {
							"mode": "raw",
							"raw": "{\n    \"email\": \"{{userEmail}}\",\n    \"password\": \"password123\"\n}"
						},
						"url": {
							"raw": "{{baseUrl}}/auth/login",
							"host": [
								"{{baseUrl}}"
							],
							"path": [
								"auth",
								"login"
							]
						}
					},
					"response": []
				},
				{
					"name": "Login Admin",
					"event": [
						{
							"listen": "test",
							"script": {
								"exec": [
									"pm.test(\"Status code is 200\", function () {",
									"    pm.response.to.have.status(200);",
									"});",
									"var jsonData = pm.response.json();",
									"if (jsonData.accessToken) {",
									"    pm.environment.set(\"authToken\", jsonData.accessToken);",
									"    pm.environment.set(\"userId\", jsonData.user.id);",
									"    console.log(\"Admin Token retrieved\");",
									"}"
								],
								"type": "text/javascript"
							}
						}
					],
					"request": {
						"method": "POST",
						"header": [
							{
								"key": "Content-Type",
								"value": "application/json"
							}
						],
						"body": {
							"mode": "raw",
							"raw": "{\n    \"email\": \"admin@bigshop.com\",\n    \"password\": \"password123\"\n}"
						},
						"url": {
							"raw": "{{baseUrl}}/auth/login",
							"host": [
								"{{baseUrl}}"
							],
							"path": [
								"auth",
								"login"
							]
						}
					},
					"response": []
				},
				{
					"name": "Refresh Token",
					"request": {
						"method": "POST",
						"header": [
							{
								"key": "Refresh-Token",
								"value": "some-refresh-token-value"
							}
						],
						"url": {
							"raw": "{{baseUrl}}/auth/refresh-token",
							"host": [
								"{{baseUrl}}"
							],
							"path": [
								"auth",
								"refresh-token"
							]
						}
					},
					"response": []
				}
			]
		},
		{
			"name": "02. Categories",
			"item": [
				{
					"name": "Get All Categories",
					"request": {
						"method": "GET",
						"header": [],
						"url": {
							"raw": "{{baseUrl}}/categories",
							"host": [
								"{{baseUrl}}"
							],
							"path": [
								"categories"
							]
						}
					},
					"response": []
				},
				{
					"name": "Get Category by ID",
					"request": {
						"method": "GET",
						"header": [],
						"url": {
							"raw": "{{baseUrl}}/categories/{{categoryId}}",
							"host": [
								"{{baseUrl}}"
							],
							"path": [
								"categories",
								"{{categoryId}}"
							]
						}
					},
					"response": []
				},
				{
					"name": "Create Category (Admin)",
					"event": [
						{
							"listen": "test",
							"script": {
								"exec": [
									"var jsonData = pm.response.json();",
									"if (jsonData.id) {",
									"    pm.environment.set(\"categoryId\", jsonData.id);",
									"}"
								],
								"type": "text/javascript"
							}
						}
					],
					"request": {
						"auth": {
							"type": "bearer",
							"bearer": [
								{
									"key": "token",
									"value": "{{authToken}}",
									"type": "string"
								}
							]
						},
						"method": "POST",
						"header": [
							{
								"key": "Content-Type",
								"value": "application/json"
							}
						],
						"body": {
							"mode": "raw",
							"raw": "{\n    \"name\": \"New Category\",\n    \"description\": \"Created via Postman\",\n    \"active\": true\n}"
						},
						"url": {
							"raw": "{{baseUrl}}/categories",
							"host": [
								"{{baseUrl}}"
							],
							"path": [
								"categories"
							]
						}
					},
					"response": []
				}
			]
		},
		{
			"name": "03. Products",
			"item": [
				{
					"name": "Get All Products",
					"request": {
						"method": "GET",
						"header": [],
						"url": {
							"raw": "{{baseUrl}}/products",
							"host": [
								"{{baseUrl}}"
							],
							"path": [
								"products"
							]
						}
					},
					"response": []
				},
				{
					"name": "Create Product (Admin)",
					"event": [
						{
							"listen": "test",
							"script": {
								"exec": [
									"var jsonData = pm.response.json();",
									"if (jsonData.id) {",
									"    pm.environment.set(\"productId\", jsonData.id);",
									"}"
								],
								"type": "text/javascript"
							}
						}
					],
					"request": {
						"auth": {
							"type": "bearer",
							"bearer": [
								{
									"key": "token",
									"value": "{{authToken}}",
									"type": "string"
								}
							]
						},
						"method": "POST",
						"header": [
							{
								"key": "Content-Type",
								"value": "application/json"
							}
						],
						"body": {
							"mode": "raw",
							"raw": "{\n    \"name\": \"New Product\",\n    \"description\": \"Awesome product\",\n    \"price\": 99.99,\n    \"stockQuantity\": 100,\n    \"categoryId\": {{categoryId}},\n    \"active\": true\n}"
						},
						"url": {
							"raw": "{{baseUrl}}/products",
							"host": [
								"{{baseUrl}}"
							],
							"path": [
								"products"
							]
						}
					},
					"response": []
				},
				{
					"name": "Get Product by ID",
					"request": {
						"method": "GET",
						"header": [],
						"url": {
							"raw": "{{baseUrl}}/products/{{productId}}",
							"host": [
								"{{baseUrl}}"
							],
							"path": [
								"products",
								"{{productId}}"
							]
						}
					},
					"response": []
				}
			]
		},
		{
			"name": "04. Cart",
			"item": [
				{
					"name": "Get Cart",
					"request": {
						"auth": {
							"type": "bearer",
							"bearer": [
								{
									"key": "token",
									"value": "{{authToken}}",
									"type": "string"
								}
							]
						},
						"method": "GET",
						"header": [],
						"url": {
							"raw": "{{baseUrl}}/cart",
							"host": [
								"{{baseUrl}}"
							],
							"path": [
								"cart"
							]
						}
					},
					"response": []
				},
				{
					"name": "Add to Cart",
					"request": {
						"auth": {
							"type": "bearer",
							"bearer": [
								{
									"key": "token",
									"value": "{{authToken}}",
									"type": "string"
								}
							]
						},
						"method": "POST",
						"header": [
							{
								"key": "Content-Type",
								"value": "application/json"
							}
						],
						"body": {
							"mode": "raw",
							"raw": "{\n    \"productId\": {{productId}},\n    \"quantity\": 2\n}"
						},
						"url": {
							"raw": "{{baseUrl}}/cart/items",
							"host": [
								"{{baseUrl}}"
							],
							"path": [
								"cart",
								"items"
							]
						}
					},
					"response": []
				},
				{
					"name": "Clear Cart",
					"request": {
						"auth": {
							"type": "bearer",
							"bearer": [
								{
									"key": "token",
									"value": "{{authToken}}",
									"type": "string"
								}
							]
						},
						"method": "DELETE",
						"header": [],
						"url": {
							"raw": "{{baseUrl}}/cart",
							"host": [
								"{{baseUrl}}"
							],
							"path": [
								"cart"
							]
						}
					},
					"response": []
				}
			]
		},
		{
			"name": "05. Addresses",
			"item": [
				{
					"name": "Create Address",
					"event": [
						{
							"listen": "test",
							"script": {
								"exec": [
									"var jsonData = pm.response.json();",
									"if (jsonData.id) {",
									"    pm.environment.set(\"addressId\", jsonData.id);",
									"}"
								],
								"type": "text/javascript"
							}
						}
					],
					"request": {
						"auth": {
							"type": "bearer",
							"bearer": [
								{
									"key": "token",
									"value": "{{authToken}}",
									"type": "string"
								}
							]
						},
						"method": "POST",
						"header": [
							{
								"key": "Content-Type",
								"value": "application/json"
							}
						],
						"body": {
							"mode": "raw",
							"raw": "{\n  \"fullName\": \"Test User\",\n  \"phone\": \"+33612345678\",\n  \"street\": \"123 Rue de Rivoli\",\n  \"city\": \"Paris\",\n  \"zipCode\": \"75001\",\n  \"country\": \"France\",\n  \"isDefault\": true\n}"
						},
						"url": {
							"raw": "{{baseUrl}}/addresses",
							"host": [
								"{{baseUrl}}"
							],
							"path": [
								"addresses"
							]
						}
					},
					"response": []
				},
				{
					"name": "Get My Addresses",
					"request": {
						"auth": {
							"type": "bearer",
							"bearer": [
								{
									"key": "token",
									"value": "{{authToken}}",
									"type": "string"
								}
							]
						},
						"method": "GET",
						"header": [],
						"url": {
							"raw": "{{baseUrl}}/addresses",
							"host": [
								"{{baseUrl}}"
							],
							"path": [
								"addresses"
							]
						}
					},
					"response": []
				}
			]
		},
		{
			"name": "06. Orders",
			"item": [
				{
					"name": "Create Order",
					"event": [
						{
							"listen": "test",
							"script": {
								"exec": [
									"var jsonData = pm.response.json();",
									"if (jsonData.id) {",
									"    pm.environment.set(\"orderId\", jsonData.id);",
									"}"
								],
								"type": "text/javascript"
							}
						}
					],
					"request": {
						"auth": {
							"type": "bearer",
							"bearer": [
								{
									"key": "token",
									"value": "{{authToken}}",
									"type": "string"
								}
							]
						},
						"method": "POST",
						"header": [
							{
								"key": "Content-Type",
								"value": "application/json"
							}
						],
						"body": {
							"mode": "raw",
							"raw": "{\n  \"addressId\": {{addressId}},\n  \"paymentMethod\": \"STRIPE\",\n  \"notes\": \"Please deliver between 9AM-5PM\"\n}"
						},
						"url": {
							"raw": "{{baseUrl}}/orders",
							"host": [
								"{{baseUrl}}"
							],
							"path": [
								"orders"
							]
						}
					},
					"response": []
				},
				{
					"name": "Get My Orders",
					"request": {
						"auth": {
							"type": "bearer",
							"bearer": [
								{
									"key": "token",
									"value": "{{authToken}}",
									"type": "string"
								}
							]
						},
						"method": "GET",
						"header": [],
						"url": {
							"raw": "{{baseUrl}}/orders/my-orders",
							"host": [
								"{{baseUrl}}"
							],
							"path": [
								"orders",
								"my-orders"
							]
						}
					},
					"response": []
				}
			]
		},
		{
			"name": "07. Admin Dashboard",
			"item": [
				{
					"name": "Get Dashboard Stats",
					"request": {
						"auth": {
							"type": "bearer",
							"bearer": [
								{
									"key": "token",
									"value": "{{authToken}}",
									"type": "string"
								}
							]
						},
						"method": "GET",
						"header": [],
						"url": {
							"raw": "{{baseUrl}}/dashboard/stats",
							"host": [
								"{{baseUrl}}"
							],
							"path": [
								"dashboard",
								"stats"
							]
						}
					},
					"response": []
				},
				{
					"name": "Get Revenue Stats",
					"request": {
						"auth": {
							"type": "bearer",
							"bearer": [
								{
									"key": "token",
									"value": "{{authToken}}",
									"type": "string"
								}
							]
						},
						"method": "GET",
						"header": [],
						"url": {
							"raw": "{{baseUrl}}/admin/revenue?startDate=2026-01-01&endDate=2026-01-31",
							"host": [
								"{{baseUrl}}"
							],
							"path": [
								"admin",
								"revenue"
							],
							"query": [
								{
									"key": "startDate",
									"value": "2026-01-01"
								},
								{
									"key": "endDate",
									"value": "2026-01-31"
								}
							]
						}
					},
					"response": []
				}
			]
		}
	]
}